python/query-agent-UPN.py
shared_mailbox_converter/clean_up.py
shared_mailbox_converter/create_csv.py
shared_mailbox_converter/setup.py
shared_mailbox_converter/python/query-agent-UPN.py
corpit.sharedmailboxconvert-0.1.0.dist-info/METADATA
corpit.sharedmailboxconvert-0.1.0.dist-info/WHEEL
corpit.sharedmailboxconvert-0.1.0.dist-info/top_level.txt
corpit.sharedmailboxconvert-0.1.0.dist-info/RECORD
