Metadata-Version: 2.1
Name: corpit.sharedmailboxconvert
Version: 0.1.0
Summary: UNKNOWN
Home-page: UNKNOWN
Author: Thaddius Cho
Author-email: mcho@assurance.com
License: UNKNOWN
Keywords: corpit,Jira,user_management
Platform: UNKNOWN
Requires-Python: >=3.8
Requires-Dist: requests (==2.24.0)
Requires-Dist: pandas (==1.1.3)
